{
  "title": "辩论的真相：赢在观众，而非对手",
  "summary": "本章揭示辩论的本质是说服观众而非对方，关键在于重新定义概念和基于逻辑的急智，帮助我们在辩论中赢得人心。",
  "turns": [
    {
      "speaker": "甲",
      "text": "大家好，欢迎收听这期节目。今天我们聊聊刘润《底层逻辑》里关于辩论的那一章，标题叫‘如何赢得一场辩论’，听起来挺实用的。"
    },
    {
      "speaker": "乙",
      "text": "没错，我读完感觉挺颠覆的。以前觉得辩论就是争个胜负，但刘润说辩论的目的根本不是说服对方，而是说服观众。"
    },
    {
      "speaker": "甲",
      "text": "对，他说对方是不可被说服的，赢了辩论也不是因为对方认输，而是观众被你影响了。这一点很关键，像很多网络争论其实都是说给围观者听的。"
    },
    {
      "speaker": "乙",
      "text": "然后他还提到一个‘暗黑的秘密’，就是辩论双方几乎从不正面辩论，而是不断重新定义概念。比如人性本善，对方说救人发自本能，你可以把‘善’重新定义为‘对整体利益的考量’，这就把对方的论点给架空了。"
    },
    {
      "speaker": "甲",
      "text": "这其实就是偷换概念，但换个好听的名字叫‘纠正对方的概念’。我觉得生活中也很常见，比如吵架时，你说‘你总是不做家务’，对方说‘我昨天还拖了地’，这就是在重新定义‘总’的频率。"
    },
    {
      "speaker": "乙",
      "text": "确实，辩论的核心不是论据本身，而是逻辑论证。刘润举了个例子，你说‘我吃了大餐所以心情好’，辩手马上拿别人吃大餐却愁眉苦脸来反驳，根本不关心你吃的什么，只是攻击逻辑漏洞。"
    },
    {
      "speaker": "甲",
      "text": "所以辩论的核心竞争力是‘基于逻辑的急智’，十秒内要完成一个回合。演讲高手反而不擅长辩论，因为演讲需要长期布局，而辩论是瞬间反应。就像罗振宇在《奇葩说》插不上话那样。"
    },
    {
      "speaker": "乙",
      "text": "但是我觉得，我们普通人不用去参加辩论赛，但懂得这些能减少很多无谓的争论。比如网上看到观点冲突，先想想对方是在陈述事实还是在表达观点，或者是不是立场问题。"
    },
    {
      "speaker": "甲",
      "text": "对，刘润之前也讲了事实、观点、立场、信仰的区分。辩论其实是把这种区分用到极致，你的目的不是改变对方，而是让旁观者看清你的逻辑。"
    },
    {
      "speaker": "乙",
      "text": "而且他提到，观众不会接受你塞给他们的观点，他们只会在安全舒适的氛围里自己取走。所以辩论要营造一种氛围，比如幽默、自信、逻辑严密，让观众觉得你靠谱。"
    },
    {
      "speaker": "甲",
      "text": "那具体怎么营造氛围呢？我觉得可以多用类比和故事，比如他举《三体》里那个心软的面壁人，说明个体善可能带来群体恶。这比枯燥地讲道理有说服力多了。"
    },
    {
      "speaker": "乙",
      "text": "没错，辩论其实是表演，观众看的不是真理，而是表演者的智慧和风度。所以刘润说，辩论能让我们看真理的眼睛更加明亮，但前提是我们要明白辩的是什么。"
    },
    {
      "speaker": "甲",
      "text": "不过有一点我挺有感触，他说很多人习惯表达但不习惯交锋。我以前觉得自己表达能力还行，但遇到杠精就手足无措，其实就是缺乏辩论训练。"
    },
    {
      "speaker": "乙",
      "text": "所以建议大家平时多练习逻辑急智，比如和朋友玩一些即兴辩论游戏，或者看辩论赛时自己分析攻防。不用真的去争输赢，主要是锻炼思维。"
    },
    {
      "speaker": "甲",
      "text": "还有一点，刘润强调了‘重新定义’的技巧，但我觉得用不好容易变成诡辩。我们还是要基于事实和逻辑，不能为赢而歪曲概念。"
    },
    {
      "speaker": "乙",
      "text": "对的，他用的词是‘纠正’而不是‘歪曲’，意思是你要找到对方定义中不严谨的地方，然后用更合理的定义去覆盖。比如‘善’的定义，到底是动机还是结果？这里面就有很多空间。"
    },
    {
      "speaker": "甲",
      "text": "所以总结一下，这一章我学到三点：第一，辩论目的是影响观众不是说服对手；第二，关键是通过重新定义概念来构建自己的逻辑；第三，核心竞争力是基于逻辑的急智。"
    },
    {
      "speaker": "乙",
      "text": "而且这些不仅用于辩论，职场开会、商务谈判、甚至日常聊天都适用。比如在项目汇报中，你要说服的是老板和同事，而不是和你争辩的人。"
    },
    {
      "speaker": "甲",
      "text": "最后刘润说‘辩与不辩，真理都一直在那里’，我觉得很有哲理。辩论只是帮我们把模糊的真理擦得更亮，但真理本身不变。"
    },
    {
      "speaker": "乙",
      "text": "好，今天就聊到这里。希望大家以后看辩论或者参与讨论时，能多一些清醒。谢谢收听，下期再见！"
    }
  ]
}